odoo/addons/base_partner_sequence_contacts/README.rst
odoo/addons/base_partner_sequence_contacts/__init__.py
odoo/addons/base_partner_sequence_contacts/__manifest__.py
odoo/addons/base_partner_sequence_contacts/models/__init__.py
odoo/addons/base_partner_sequence_contacts/models/res_partner.py
odoo/addons/base_partner_sequence_contacts/static/description/icon.png
odoo_addon_base_partner_sequence_contacts-16.0.1.0.0.2.dist-info/METADATA
odoo_addon_base_partner_sequence_contacts-16.0.1.0.0.2.dist-info/WHEEL
odoo_addon_base_partner_sequence_contacts-16.0.1.0.0.2.dist-info/top_level.txt
odoo_addon_base_partner_sequence_contacts-16.0.1.0.0.2.dist-info/RECORD
